{"pasado": {"el": {"ladino": "embreneo", "source": "embrenear.yaml", "translations": {}}, "eyos": {"ladino": "embrenearon", "source": "embrenear.yaml", "translations": {}}, "mozotros": {"ladino": "embreneimos", "source": "embrenear.yaml", "translations": {}}, "tu": {"ladino": "embreneates", "source": "embrenear.yaml", "translations": {}}, "vozotros": {"ladino": "embreneatesh", "source": "embrenear.yaml", "translations": {}}, "yo": {"ladino": "embrenei", "source": "embrenear.yaml", "translations": {}}}, "prezente": {"el": {"ladino": "embrenea", "source": "embrenear.yaml", "translations": {}}, "eyos": {"ladino": "embrenean", "source": "embrenear.yaml", "translations": {}}, "mozotros": {"ladino": "embreneamos", "source": "embrenear.yaml", "translations": {}}, "tu": {"ladino": "embreneas", "source": "embrenear.yaml", "translations": {}}, "vozotros": {"ladino": "embreneash", "source": "embrenear.yaml", "translations": {}}, "yo": {"ladino": "embreneo", "source": "embrenear.yaml", "translations": {}}}}