{"imperfekto": {"el": {"ladino": "esperava", "source": "esperar.yaml", "translations": {}}, "eyos": {"ladino": "esperavan", "source": "esperar.yaml", "translations": {}}, "mozotros": {"ladino": "esperavamos", "source": "esperar.yaml", "translations": {}}, "tu": {"ladino": "esperavas", "source": "esperar.yaml", "translations": {}}, "vozotros": {"ladino": "esperavash", "source": "esperar.yaml", "translations": {}}, "yo": {"ladino": "esperava", "source": "esperar.yaml", "translations": {}}}, "pasado": {"el": {"ladino": "espero", "source": "esperar.yaml", "translations": {}}, "eyos": {"ladino": "esperaron", "source": "esperar.yaml", "translations": {}}, "mozotros": {"ladino": "esperimos", "source": "esperar.yaml", "translations": {}}, "tu": {"ladino": "esperates", "source": "esperar.yaml", "translations": {}}, "vozotros": {"ladino": "esperatesh", "source": "esperar.yaml", "translations": {}}, "yo": {"ladino": "esperi", "source": "esperar.yaml", "translations": {}}}, "prezente": {"el": {"ladino": "espera", "source": "esperar.yaml", "translations": {"english": ["hopes"], "spanish": ["espera"]}}, "eyos": {"ladino": "esperan", "source": "esperar.yaml", "translations": {"english": ["hope"], "spanish": ["esperan"]}}, "mozotros": {"ladino": "esperamos", "source": "esperar.yaml", "translations": {"english": ["hope"], "spanish": ["esperamos"]}}, "tu": {"ladino": "esperas", "source": "esperar.yaml", "translations": {"english": ["hope"], "spanish": ["esperas"]}}, "vozotros": {"ladino": "esperash", "source": "esperar.yaml", "translations": {"english": ["hope"], "spanish": ["esperáis"]}}, "yo": {"ladino": "espero", "source": "esperar.yaml", "translations": {"english": ["hope"], "spanish": ["espero"]}}}}