{"pasado": {"el": {"ladino": "kazo", "source": "kazar.yaml", "translations": {}}, "eyos": {"ladino": "kazaron", "source": "kazar.yaml", "translations": {}}, "mozotros": {"ladino": "kazimos", "source": "kazar.yaml", "translations": {}}, "tu": {"ladino": "kazates", "source": "kazar.yaml", "translations": {}}, "vozotros": {"ladino": "kazatesh", "source": "kazar.yaml", "translations": {}}, "yo": {"ladino": "kazi", "source": "kazar.yaml", "translations": {}}}, "prezente": {"el": {"ladino": "kaza", "source": "kazar.yaml", "translations": {}}, "eyos": {"ladino": "kazan", "source": "kazar.yaml", "translations": {}}, "mozotros": {"ladino": "kazamos", "source": "kazar.yaml", "translations": {}}, "tu": {"ladino": "kazas", "source": "kazar.yaml", "translations": {}}, "vozotros": {"ladino": "kazash", "source": "kazar.yaml", "translations": {}}, "yo": {"ladino": "kazo", "source": "kazar.yaml", "translations": {}}}}