{"imperfekto": {"el": {"ladino": "kresia", "source": "kreser.yaml", "translations": {}}, "eyos": {"ladino": "kresian", "source": "kreser.yaml", "translations": {}}, "mozotros": {"ladino": "kresiamos", "source": "kreser.yaml", "translations": {}}, "tu": {"ladino": "kresias", "source": "kreser.yaml", "translations": {}}, "vozotros": {"ladino": "kresiash", "source": "kreser.yaml", "translations": {}}, "yo": {"ladino": "kresia", "source": "kreser.yaml", "translations": {}}}, "pasado": {"el": {"ladino": "kresio", "source": "kreser.yaml", "translations": {}}, "eyos": {"ladino": "kresieron", "source": "kreser.yaml", "translations": {}}, "mozotros": {"ladino": "kresimos", "source": "kreser.yaml", "translations": {}}, "tu": {"ladino": "kresites", "source": "kreser.yaml", "translations": {}}, "vozotros": {"ladino": "kresitesh", "source": "kreser.yaml", "translations": {}}, "yo": {"ladino": "kresi", "source": "kreser.yaml", "translations": {}}}, "prezente": {"el": {"ladino": "krese", "source": "kreser.yaml", "translations": {}}, "eyos": {"ladino": "kresen", "source": "kreser.yaml", "translations": {}}, "mozotros": {"ladino": "kresemos", "source": "kreser.yaml", "translations": {}}, "tu": {"ladino": "kreses", "source": "kreser.yaml", "translations": {}}, "vozotros": {"ladino": "kresesh", "source": "kreser.yaml", "translations": {}}, "yo": {"ladino": "kreso", "source": "kreser.yaml", "translations": {}}}}