{"pasado": {"el": {"ladino": "provo", "source": "provar.yaml", "translations": {}}, "eyos": {"ladino": "provaron", "source": "provar.yaml", "translations": {}}, "mozotros": {"ladino": "provimos", "source": "provar.yaml", "translations": {}}, "tu": {"ladino": "provates", "source": "provar.yaml", "translations": {}}, "vozotros": {"ladino": "provatesh", "source": "provar.yaml", "translations": {}}, "yo": {"ladino": "provi", "source": "provar.yaml", "translations": {}}}, "prezente": {"el": {"ladino": "prova", "source": "provar.yaml", "translations": {}}, "eyos": {"ladino": "provan", "source": "provar.yaml", "translations": {}}, "mozotros": {"ladino": "provamos", "source": "provar.yaml", "translations": {}}, "tu": {"ladino": "provas", "source": "provar.yaml", "translations": {}}, "vozotros": {"ladino": "provash", "source": "provar.yaml", "translations": {}}, "yo": {"ladino": "provo", "source": "provar.yaml", "translations": {}}}}