[{"accented": "arrepushar", "alternative-spelling": [{"accented": "arrondjar", "ladino": "arrondjar"}], "ladino": "arrepushar", "source": "arrepushar.yaml", "translations": {"english": ["push", "shove"], "french": [], "portuguese": [], "spanish": ["empujar"], "turkish": ["itmek"]}}, {"accented": "arrondjár", "ladino": "arrondjar", "source": "arrondjar.yaml", "translations": {"english": ["push", "expel", "shove"], "french": [], "portuguese": [], "spanish": ["empujar", "expulsar"], "turkish": ["itmek", "iteklemek"]}}]