[{"accented": "doméstiko", "alternative-spelling": [{"accented": "de kaza", "ladino": "de kaza"}], "examples": [{"ladino": "Los programas inkluyen volos domestikos en Argentina. "}], "gender": "masculine", "ladino": "domestiko", "number": "singular", "source": "domestiko.yaml", "translations": {"english": ["domestic"], "french": ["domestique"], "portuguese": [], "spanish": ["domestico"], "turkish": ["evle ilgili", "evcil"]}}, {"accented": "doméstikos", "alternative-spelling": [{"accented": "de kaza", "ladino": "de kaza"}], "gender": "masculine", "ladino": "domestikos", "number": "plural", "source": "domestiko.yaml", "translations": {"english": ["domestic"], "french": ["domestique"], "portuguese": [], "spanish": ["domesticos"], "turkish": ["evle ilgili", "evcil"]}}]