[{"accented": "ésto", "gender": "masculine", "ladino": "esto", "number": "singular", "origen": "Jeneral", "source": "este.yaml", "translations": {"english": ["this"], "french": [], "portuguese": [], "spanish": ["esto"], "turkish": ["bu"]}, "xexamples": [{"example": {"english": "I am sure", "ladino": "Esto seguro", "ladino_html": "<a href=\"/words/ladino/esto\">Esto</a> <a href=\"/words/ladino/seguro\">seguro</a>"}, "source": "words.yaml", "url": "esto-seguro"}, {"example": {"english": "I am in Jerusalem", "ladino": "yo esto en Yerushalayim", "ladino_html": "<a href=\"/words/ladino/yo\">yo</a> <a href=\"/words/ladino/esto\">esto</a> <a href=\"/words/ladino/en\">en</a> <a href=\"/words/ladino/yerushalayim\">Yerushalayim</a>"}, "source": "sentences.yaml", "url": "yo-esto-en-yerushalayim"}, {"example": {"english": "I am here", "ladino": "yo esto aki", "ladino_html": "<a href=\"/words/ladino/yo\">yo</a> <a href=\"/words/ladino/esto\">esto</a> <a href=\"/words/ladino/aki\">aki</a>"}, "source": "sentences.yaml", "url": "yo-esto-aki"}, {"example": {"english": "I am not here", "ladino": "yo no esto aki", "ladino_html": "<a href=\"/words/ladino/yo\">yo</a> <a href=\"/words/ladino/no\">no</a> <a href=\"/words/ladino/esto\">esto</a> <a href=\"/words/ladino/aki\">aki</a>"}, "source": "sentences.yaml", "url": "yo-no-esto-aki"}, {"example": {"english": "Thank you David. I am very well.", "ladino": "Grasias, David. Esto muy bien.", "ladino_html": "<a href=\"/words/ladino/grasias\">Grasias</a>, David. <a href=\"/words/ladino/esto\">Esto</a> <a href=\"/words/ladino/muy\">muy</a> <a href=\"/words/ladino/bien\">bien</a>."}, "source": "sentences.yaml", "url": "grasias-david-esto-muy-bien"}, {"example": {"english": "I am in the kitchen", "ladino": "Esto en la kuzina", "ladino_html": "<a href=\"/words/ladino/esto\">Esto</a> <a href=\"/words/ladino/en\">en</a> <a href=\"/words/ladino/la\">la</a> <a href=\"/words/ladino/kuzina\">kuzina</a>"}, "source": "sentences.yaml", "url": "esto-en-la-kuzina"}]}]