[{"accented": "kuántos", "examples": [{"ladino": "Muera Shimshon kon kuantos son."}], "gender": "masculine", "ladino": "kuantos", "origen": "Jeneral", "source": "kuantos.yaml", "translations": {"english": ["how many", "all those"], "french": [], "portuguese": [], "spanish": ["cuantos"], "turkish": ["kaç tane", "hepsi"]}, "xexamples": [{"example": {"english": "How old are you?", "ladino": "Kuantos anyos tienes?", "ladino_html": "<a href=\"/words/ladino/kuantos\">Kuantos</a> <a href=\"/words/ladino/anyos\">anyos</a> <a href=\"/words/ladino/tienes\">tienes</a>?"}, "source": "questions.yaml", "url": "kuantos-anyos-tienes"}]}]