[{"ladino": "viajas", "source": "viajar.yaml", "translations": {"english": ["travel"], "spanish": ["vijas"]}, "xexamples": [{"example": {"english": "Do you travel by car or by bus?", "ladino": "Tu viajas kon oto o kon otobus?", "ladino_html": "<a href=\"/words/ladino/tu\">Tu</a> <a href=\"/words/ladino/viajas\">viajas</a> <a href=\"/words/ladino/kon\">kon</a> <a href=\"/words/ladino/oto\">oto</a> <a href=\"/words/ladino/o\">o</a> <a href=\"/words/ladino/kon\">kon</a> <a href=\"/words/ladino/otobus\">otobus</a>?"}, "source": "transportation.yaml", "url": "tu-viajas-kon-oto-o-kon-otobus"}]}]