[{"accented": "viérnes", "alternative-spelling": [{"ladino": "vyernes"}], "examples": [{"ladino": "Oy es viernes, pitikas kayentes."}, {"english": "In Israel every Friday the whole family has dinner together.", "ladino": "En Israel kada viernes toda la famiya sena endjuntos."}], "gender": "masculine", "ladino": "viernes", "number": "singular", "source": "viernes.yaml", "translations": {"english": ["Friday"], "french": [], "hebrew": ["יום שישי", "יום ו"], "portuguese": [], "spanish": ["viernes"], "turkish": ["cuma"]}}]